divisi/__init__.py
divisi/discretization.py
divisi/filters.py
divisi/projections.py
divisi/ranking.py
divisi/recursive.py
divisi/sampling.py
divisi/spark.py
divisi/subgroups.py
divisi/utils.py
divisi/widget.py
divisi/static/style.css
divisi/static/widget-main.js
divisi_toolkit-0.3.0.dist-info/licenses/LICENSE
divisi_toolkit-0.3.0.dist-info/METADATA
divisi_toolkit-0.3.0.dist-info/WHEEL
divisi_toolkit-0.3.0.dist-info/top_level.txt
divisi_toolkit-0.3.0.dist-info/RECORD
