Metadata-Version: 2.4
Name: divisi-toolkit
Version: 0.3.0
Summary: Interactive widget and toolkit for slice discovery
Author-email: Venkatesh Sivaraman <venkats@cmu.edu>
License: MIT License
Project-URL: Homepage, https://github.com/cmudig/divisi-toolkit
Keywords: AI,machine learning,notebook,jupyter,data science
Classifier: Programming Language :: Python :: 3
Classifier: License :: OSI Approved :: MIT License
Requires-Python: >=3.7
License-File: LICENSE
Requires-Dist: scipy
Requires-Dist: scikit-learn
Requires-Dist: numpy
Requires-Dist: ipywidgets
Requires-Dist: anywidget
Requires-Dist: torch
Requires-Dist: tqdm
Dynamic: license-file
